xcodelocalize/Settings.py
xcodelocalize/Strings.py
xcodelocalize/Translator.py
xcodelocalize/__init__.py
xcodelocalize/__main__.py
xcodelocalize/main.py
xcodelocalize-1.0.3.dist-info/LICENSE
xcodelocalize-1.0.3.dist-info/METADATA
xcodelocalize-1.0.3.dist-info/WHEEL
xcodelocalize-1.0.3.dist-info/entry_points.txt
xcodelocalize-1.0.3.dist-info/RECORD
