Metadata-Version: 2.1
Name: xcodelocalize
Version: 1.0.3
Summary: Tool for automatic search and localization of .strings files
Home-page: https://pypi.org/project/xcodelocalize/
License: MIT
Keywords: xcode,localize,strings,localization,ios
Author: MarkParker5
Author-email: markparker.it@gmail.com
Requires-Python: >=3.9,<4.0
Classifier: License :: OSI Approved :: MIT License
Classifier: Programming Language :: Python :: 3
Classifier: Programming Language :: Python :: 3.9
Classifier: Programming Language :: Python :: 3.10
Classifier: Programming Language :: Python :: 3.11
Requires-Dist: mtranslate (>=1.8,<2.0)
Requires-Dist: typer[all] (>=0.7.0,<0.8.0)
Project-URL: Documentation, https://github.com/MarkParker5/XCodeLocalize/blob/main/README.md
Project-URL: Repository, https://github.com/MarkParker5/XCodeLocalize
